{
  "dialog_id": 708,
  "client_profile": {
    "source": "taskmaster-1",
    "domain": "coffee-ordering-1",
    "text": "Taskmaster: coffee-ordering order.",
    "regLine": "source=taskmaster domain=coffee-ordering-1 dialog_id=708"
  },
  "turns": [
    {
      "speaker": "client",
      "text": "I want to place an order for pick-up for some coffee."
    },
    {
      "speaker": "cashier",
      "text": "Hi how are you?"
    },
    {
      "speaker": "cashier",
      "text": "starbucks or peets?"
    },
    {
      "speaker": "client",
      "text": "the Starbucks on University Avenue in Madison, Wisconsin."
    },
    {
      "speaker": "cashier",
      "text": "great and what would you like?"
    },
    {
      "speaker": "client",
      "text": "Want an iced cafe mocha."
    },
    {
      "speaker": "cashier",
      "text": "great and what size?"
    },
    {
      "speaker": "client",
      "text": "grande."
    },
    {
      "speaker": "cashier",
      "text": "what milk would you like?"
    },
    {
      "speaker": "client",
      "text": "whole milk."
    },
    {
      "speaker": "cashier",
      "text": "any add ons or whipped cream?"
    },
    {
      "speaker": "client",
      "text": "Can I get it without whip cream?"
    },
    {
      "speaker": "cashier",
      "text": "So that's a grande iced cafe mocha with whole milk, no whipped cream from the starbucks in madison."
    },
    {
      "speaker": "client",
      "text": "You got it."
    },
    {
      "speaker": "cashier",
      "text": "you're all set, your drink will be ready in 15 minutes and you'll get a receipt via text."
    },
    {
      "speaker": "client",
      "text": "Okay. Thanks."
    },
    {
      "speaker": "cashier",
      "text": "no problem, bye."
    }
  ],
  "final_order": {
    "items": [
      {
        "name": "cafe mocha",
        "quantity": 1,
        "energy": 0
      },
      {
        "name": "grande",
        "quantity": 1,
        "energy": 0
      }
    ],
    "total_energy": 0,
    "allergens_in_order": []
  },
  "total_energy": 0,
  "validation_flags": {
    "allergen_violation": false,
    "calorie_warning": false,
    "hallucination": false,
    "incomplete_order": false
  },
  "source": "taskmaster-1-woz",
  "original_conversation_id": "dlg-62a38d4f-766c-4086-8b01-fa93b81240f7",
  "created_at": "2026-02-15T15:44:16.968Z"
}