{
  "dialog_id": 2331,
  "client_profile": {
    "source": "taskmaster-1",
    "domain": "pizza-ordering-1",
    "text": "Taskmaster: pizza-ordering order.",
    "regLine": "source=taskmaster domain=pizza-ordering-1 dialog_id=2331"
  },
  "turns": [
    {
      "speaker": "client",
      "text": "I'd like to place a pizza order for delivery please. "
    },
    {
      "speaker": "cashier",
      "text": "With whom would you like to make this purchase?"
    },
    {
      "speaker": "client",
      "text": "I want to use Blaze pizza."
    },
    {
      "speaker": "cashier",
      "text": "Where will they be delivering the pizza to?"
    },
    {
      "speaker": "client",
      "text": "At the Law Library at NSU. "
    },
    {
      "speaker": "cashier",
      "text": "To whom will this be delivered to?"
    },
    {
      "speaker": "client",
      "text": "Alex, they already have all my info on file. "
    },
    {
      "speaker": "cashier",
      "text": "I pulled up the info and Im ready if you know what you want to get."
    },
    {
      "speaker": "client",
      "text": "I would like to get a extra large pizza."
    },
    {
      "speaker": "cashier",
      "text": "What toppings do you want?"
    },
    {
      "speaker": "client",
      "text": "Apple wood bacon and pepperoni."
    },
    {
      "speaker": "cashier",
      "text": "What type of cheese will you like with that?"
    },
    {
      "speaker": "client",
      "text": "I want mozzarella and Parmesan."
    },
    {
      "speaker": "cashier",
      "text": "What will you like for the sauce?"
    },
    {
      "speaker": "client",
      "text": "I would like the spicy red sauce."
    },
    {
      "speaker": "cashier",
      "text": "Will that be it?"
    },
    {
      "speaker": "client",
      "text": "Yes, it will. "
    },
    {
      "speaker": "cashier",
      "text": "Your order of one extra large pizza with apple wood bacon and pepperoni, mozzarella and parmasean cheese, spicy red sauce will be ready in 30 minutes for delivery. The total will be 24 dollars."
    },
    {
      "speaker": "client",
      "text": "Thank you"
    },
    {
      "speaker": "cashier",
      "text": "You're welcome. "
    }
  ],
  "final_order": {
    "items": [
      {
        "name": "Blaze pizza",
        "quantity": 1,
        "energy": 0
      },
      {
        "name": "Blaze pizza.",
        "quantity": 1,
        "energy": 0
      },
      {
        "name": "extra large",
        "quantity": 1,
        "energy": 0
      },
      {
        "name": "Apple wood bacon",
        "quantity": 1,
        "energy": 0
      },
      {
        "name": "pepperoni",
        "quantity": 1,
        "energy": 0
      },
      {
        "name": "mozzarella",
        "quantity": 1,
        "energy": 0
      },
      {
        "name": "mozzarella and Parmesan",
        "quantity": 1,
        "energy": 0
      },
      {
        "name": "Parmesan",
        "quantity": 1,
        "energy": 0
      },
      {
        "name": "spicy red sauce",
        "quantity": 1,
        "energy": 0
      },
      {
        "name": "spicy red sauce.",
        "quantity": 1,
        "energy": 0
      },
      {
        "name": "apple wood bacon",
        "quantity": 1,
        "energy": 0
      },
      {
        "name": "mozzarella and parmasean cheese",
        "quantity": 1,
        "energy": 0
      },
      {
        "name": "parmasean cheese",
        "quantity": 1,
        "energy": 0
      }
    ],
    "total_energy": 0,
    "allergens_in_order": []
  },
  "total_energy": 0,
  "validation_flags": {
    "allergen_violation": false,
    "calorie_warning": false,
    "hallucination": false,
    "incomplete_order": false
  },
  "source": "taskmaster-1-self",
  "original_conversation_id": "dlg-92d35cae-5d6b-4290-8098-92f5f55c9e9f",
  "created_at": "2026-02-15T15:44:17.170Z"
}