{
  "dialog_id": 2562,
  "client_profile": {
    "source": "taskmaster-1",
    "domain": "pizza-ordering-1",
    "text": "Taskmaster: pizza-ordering order.",
    "regLine": "source=taskmaster domain=pizza-ordering-1 dialog_id=2562"
  },
  "turns": [
    {
      "speaker": "client",
      "text": "Hi, I need some pizzas?"
    },
    {
      "speaker": "cashier",
      "text": "Pizzas? Not just PIzza? How many?"
    },
    {
      "speaker": "client",
      "text": "I think 4. No, make that 3."
    },
    {
      "speaker": "cashier",
      "text": "Ok, where from."
    },
    {
      "speaker": "client",
      "text": "Jet's on Telegraph Road."
    },
    {
      "speaker": "cashier",
      "text": "Ok, I see that. What do you want."
    },
    {
      "speaker": "client",
      "text": "I want 3 8-corner pizzas, all well-done. The first one is pepperonie and double cheese, nothing else."
    },
    {
      "speaker": "cashier",
      "text": "Ok, got that. Next?"
    },
    {
      "speaker": "client",
      "text": "Next one is half double-cheese and pepperonie, other side pepperoni, ham, and onion."
    },
    {
      "speaker": "cashier",
      "text": "Ok, and the last one?"
    },
    {
      "speaker": "client",
      "text": "One half is pineapple and ham, blech, and the other is mushroom, black olives, onions, and double-cheese for my anemic vegetarian niece."
    },
    {
      "speaker": "cashier",
      "text": "Ok, let me read this back to you. I have 3 8-corner pizzas, all well done. The first has double-cheese and pepperoni. The second has double cheese and pepperoni on one side, and the other side is pepperoni, ham, and onion, and the 3rd is an 8-corner, one side ham and pineapple, the other is double-cheese, mushroom, black olives, and onion."
    },
    {
      "speaker": "client",
      "text": "Wow, you got it the first time. And all well-done."
    },
    {
      "speaker": "cashier",
      "text": "Ok, all well-done. Do you want pop?"
    },
    {
      "speaker": "client",
      "text": "No, I'm a pig not an imbecile, no pops."
    },
    {
      "speaker": "cashier",
      "text": "Ok I'm ordering that now, over on Telegraph Road."
    },
    {
      "speaker": "client",
      "text": "Yep, and use my login."
    },
    {
      "speaker": "cashier",
      "text": "I did, and there's no discount. Ok, the total comes to $69.73 with tax, it should be ready in about 25 minutes."
    },
    {
      "speaker": "client",
      "text": "Dear sweet Moses, a pox on inflation. Ok, I'll be there."
    },
    {
      "speaker": "cashier",
      "text": "The receipt should be reaching your phone now. Anything else?"
    },
    {
      "speaker": "client",
      "text": "Nope, bye."
    },
    {
      "speaker": "cashier",
      "text": "Bye."
    }
  ],
  "final_order": {
    "items": [
      {
        "name": "Jet's",
        "quantity": 1,
        "energy": 0
      },
      {
        "name": "Telegraph Road",
        "quantity": 1,
        "energy": 0
      },
      {
        "name": "Telegraph Road.",
        "quantity": 1,
        "energy": 0
      },
      {
        "name": "pepperonie",
        "quantity": 1,
        "energy": 0
      },
      {
        "name": "double cheese",
        "quantity": 1,
        "energy": 0
      },
      {
        "name": "double-cheese",
        "quantity": 1,
        "energy": 0
      },
      {
        "name": "pepperoni",
        "quantity": 1,
        "energy": 0
      },
      {
        "name": "ham",
        "quantity": 1,
        "energy": 0
      },
      {
        "name": "onion",
        "quantity": 1,
        "energy": 0
      },
      {
        "name": "pineapple",
        "quantity": 1,
        "energy": 0
      },
      {
        "name": "blech",
        "quantity": 1,
        "energy": 0
      },
      {
        "name": "mushroom",
        "quantity": 1,
        "energy": 0
      },
      {
        "name": "black olives",
        "quantity": 1,
        "energy": 0
      },
      {
        "name": "onions",
        "quantity": 1,
        "energy": 0
      }
    ],
    "total_energy": 0,
    "allergens_in_order": []
  },
  "total_energy": 0,
  "validation_flags": {
    "allergen_violation": false,
    "calorie_warning": false,
    "hallucination": false,
    "incomplete_order": false
  },
  "source": "taskmaster-1-self",
  "original_conversation_id": "dlg-d0a83758-33ed-4d98-b632-b6e57dae7064",
  "created_at": "2026-02-15T15:44:17.198Z"
}