{
  "dialog_id": 2205,
  "client_profile": {
    "source": "taskmaster-1",
    "domain": "pizza-ordering-1",
    "text": "Taskmaster: pizza-ordering order.",
    "regLine": "source=taskmaster domain=pizza-ordering-1 dialog_id=2205"
  },
  "turns": [
    {
      "speaker": "client",
      "text": "We are going to do pizza from Gionino's for dinner tonight can you place the order for us?"
    },
    {
      "speaker": "cashier",
      "text": "Yes, the Gionino's in Hudson?"
    },
    {
      "speaker": "client",
      "text": "Yes please I want to pick it up."
    },
    {
      "speaker": "cashier",
      "text": "Absolutely. What can I get for you?"
    },
    {
      "speaker": "client",
      "text": "I want a white pizza and a hawaiian pizza."
    },
    {
      "speaker": "cashier",
      "text": "Ok great what sizes?"
    },
    {
      "speaker": "client",
      "text": "Medium. I think they have a special tonight, 2 medium pizzas for 16.95."
    },
    {
      "speaker": "cashier",
      "text": "They do have that special but it is for one topping pizzas not specialty pizzas."
    },
    {
      "speaker": "client",
      "text": "Oh dang it. Ok well I guess since their is no special price lets just go large on both of them."
    },
    {
      "speaker": "cashier",
      "text": "Ok, one large Hawaiian and one large white pizza.That is 48 dollars."
    },
    {
      "speaker": "client",
      "text": "Ok. Sounds good. Actually can you add a small garden pizza I just realized one of my guests is vegeterian."
    },
    {
      "speaker": "cashier",
      "text": "Yes that is another 10 dollars. So the total will be 58 dollars. One small veggie pizza, a large hawaiian and a large white pizza. For pickup. Anything else?"
    },
    {
      "speaker": "client",
      "text": "Maybe a 2 liter of pepsi? "
    },
    {
      "speaker": "cashier",
      "text": "They actually only have coke products. "
    },
    {
      "speaker": "client",
      "text": "Ok coke is fine. "
    },
    {
      "speaker": "cashier",
      "text": "Ok that is 2.75 a bottle. Just one? "
    },
    {
      "speaker": "client",
      "text": "No, let's get two. "
    },
    {
      "speaker": "cashier",
      "text": "Alright that makes your grand total 64 dollars. "
    },
    {
      "speaker": "client",
      "text": "Perfect! "
    },
    {
      "speaker": "cashier",
      "text": "Alright your large hawaiian, large white pizza, small veggie pizza and two two liters of coke will be 64 dollars should take about 25 minutes for pickup."
    },
    {
      "speaker": "client",
      "text": "Fantastic thank you so much. You can swing by and have a slice if you are out and about. "
    },
    {
      "speaker": "cashier",
      "text": "Oh I just ate but thank you and enjoy your dinner. I will see you tomorrow. "
    }
  ],
  "final_order": {
    "items": [
      {
        "name": "Gionino's",
        "quantity": 1,
        "energy": 0
      },
      {
        "name": "Hudson",
        "quantity": 1,
        "energy": 0
      },
      {
        "name": "I want a white",
        "quantity": 1,
        "energy": 0
      },
      {
        "name": "white pizza",
        "quantity": 1,
        "energy": 0
      },
      {
        "name": "hawaiian pizza",
        "quantity": 1,
        "energy": 0
      },
      {
        "name": "Medium",
        "quantity": 1,
        "energy": 0
      },
      {
        "name": "medium",
        "quantity": 1,
        "energy": 0
      },
      {
        "name": "large",
        "quantity": 1,
        "energy": 0
      },
      {
        "name": "Hawaiian",
        "quantity": 1,
        "energy": 0
      },
      {
        "name": "white pizza.",
        "quantity": 1,
        "energy": 0
      },
      {
        "name": "small",
        "quantity": 1,
        "energy": 0
      },
      {
        "name": "garden pizza",
        "quantity": 1,
        "energy": 0
      },
      {
        "name": "veggie pizza",
        "quantity": 1,
        "energy": 0
      },
      {
        "name": "hawaiian",
        "quantity": 1,
        "energy": 0
      }
    ],
    "total_energy": 0,
    "allergens_in_order": []
  },
  "total_energy": 0,
  "validation_flags": {
    "allergen_violation": false,
    "calorie_warning": false,
    "hallucination": false,
    "incomplete_order": false
  },
  "source": "taskmaster-1-self",
  "original_conversation_id": "dlg-71d4d33b-ccb8-40ec-ad82-6c48e8551969",
  "created_at": "2026-02-15T15:44:17.156Z"
}